Metadata-Version: 2.1
Name: prj
Version: 0.3.1
Summary: Setup path dependencies of a (Windows) python project from any submodule, or via interactive shell/IDLE.
Home-page: https://github.com/binares/prj
Author: binares
Author-email: binares@protonmail.com
License: MIT
Platform: UNKNOWN
Requires-Python: >=3.4
